TracAdvParseArgsPlugin-0.4.dist-info/METADATA
TracAdvParseArgsPlugin-0.4.dist-info/RECORD
TracAdvParseArgsPlugin-0.4.dist-info/WHEEL
TracAdvParseArgsPlugin-0.4.dist-info/entry_points.txt
TracAdvParseArgsPlugin-0.4.dist-info/top_level.txt
tracadvparseargs/__init__.py
tracadvparseargs/macro.py
tracadvparseargs/parseargs.py
