Metadata-Version: 2.1
Name: TracAdvParseArgsPlugin
Version: 0.4
Summary: Advanced argument parser for Trac macros.
Home-page: http://www.trac-hacks.org/wiki/AdvParseArgsPlugin
Author: Martin Scharrer
Author-email: martin@scharrer-online.de
License: BSD 3-Clause
Keywords: trac plugin parse argument
Platform: UNKNOWN
Classifier: Framework :: Trac
Requires-Dist: Trac
